README.rst
flask_cassandradb.py
setup.py
Flask-CassandraDB/__init__.py
Flask_CassandraDB.egg-info/PKG-INFO
Flask_CassandraDB.egg-info/SOURCES.txt
Flask_CassandraDB.egg-info/dependency_links.txt
Flask_CassandraDB.egg-info/pbr.json
Flask_CassandraDB.egg-info/requires.txt
Flask_CassandraDB.egg-info/top_level.txt