Metadata-Version: 1.1
Name: Flask-CassandraDB
Version: 0.0.1
Summary: connect cassandra to flask
Home-page: https://github.com/youngking/flask-cassandradb
Author: Young King
Author-email: yanckin@gmail.com
License: UNKNOWN
Platform: UNKNOWN
Classifier: Development Status :: 2 - Pre-Alpha
Classifier: Programming Language :: Python
Classifier: Programming Language :: Python :: 2
Classifier: Programming Language :: Python :: 2.7
Classifier: Programming Language :: Python :: 3
Classifier: Programming Language :: Python :: 3.4
